mhddq/__init__.py
mhddq/_impl.py
mhddq/mhddq.py
mhddq-0.3.0.dist-info/LICENSE
mhddq-0.3.0.dist-info/METADATA
mhddq-0.3.0.dist-info/WHEEL
mhddq-0.3.0.dist-info/top_level.txt
mhddq-0.3.0.dist-info/RECORD
