Metadata-Version: 2.1
Name: mhddq
Version: 0.3.0
Summary: Module implementing a multi-threaded hdd io queue.
Home-page: https://github.com/wuotes/mhddq
Author: Jordan Schaffrin
Author-email: mailbox@xrtuen.com
License: Mozilla Public License 2.0
Download-URL: https://pypi.org/project/mhddq/
Platform: UNKNOWN
Classifier: License :: OSI Approved :: Mozilla Public License 2.0 (MPL 2.0)
Classifier: Programming Language :: Python :: 3.9
Classifier: Programming Language :: Python :: 3.10
Classifier: Programming Language :: Python :: 3.11
Classifier: Programming Language :: Python :: 3.12
Classifier: Operating System :: Microsoft :: Windows
Classifier: Operating System :: POSIX :: Linux
Classifier: Operating System :: MacOS
Requires-Python: >=3.9
License-File: LICENSE
